LICENSE
MANIFEST.in
README.rst
setup.py
django_simple_settings.egg-info/PKG-INFO
django_simple_settings.egg-info/SOURCES.txt
django_simple_settings.egg-info/dependency_links.txt
django_simple_settings.egg-info/requires.txt
django_simple_settings.egg-info/top_level.txt
simple_settings/__init__.py
simple_settings/admin.py
simple_settings/context_processors.py
simple_settings/models.py